{
"meta":{"test_sets":[],"test_metrics":[],"learn_metrics":[{"best_value":"Min","name":"Logloss"}],"launch_mode":"Train","parameters":"","iteration_count":250,"learn_sets":["learn"],"name":"experiment"},
"iterations":[
{"learn":[0.5572824604],"iteration":0,"passed_time":0.1727681205,"remaining_time":43.01926201},
{"learn":[0.5440263166],"iteration":1,"passed_time":0.219143746,"remaining_time":27.17382451},
{"learn":[0.5377394442],"iteration":2,"passed_time":0.2578520853,"remaining_time":21.22982169},
{"learn":[0.534636611],"iteration":3,"passed_time":0.2963742818,"remaining_time":18.22701833},
{"learn":[0.5311753669],"iteration":4,"passed_time":0.3337295485,"remaining_time":16.35274788},
{"learn":[0.5290508131],"iteration":5,"passed_time":0.3704505345,"remaining_time":15.0649884},
{"learn":[0.5268755727],"iteration":6,"passed_time":0.4083146015,"remaining_time":14.17434974},
{"learn":[0.5246120603],"iteration":7,"passed_time":0.4490424922,"remaining_time":13.58353539},
{"learn":[0.5225128817],"iteration":8,"passed_time":0.4901680496,"remaining_time":13.12561111},
{"learn":[0.5206074051],"iteration":9,"passed_time":0.5294644401,"remaining_time":12.70714656},
{"learn":[0.5180052493],"iteration":10,"passed_time":0.56628772,"remaining_time":12.30388774},
{"learn":[0.5166014762],"iteration":11,"passed_time":0.6071537433,"remaining_time":12.04188258},
{"learn":[0.5145482194],"iteration":12,"passed_time":0.6448039689,"remaining_time":11.75527236},
{"learn":[0.5123302458],"iteration":13,"passed_time":0.6830752702,"remaining_time":11.51469741},
{"learn":[0.5101935652],"iteration":14,"passed_time":0.7231752903,"remaining_time":11.32974621},
{"learn":[0.5079077657],"iteration":15,"passed_time":0.7625765349,"remaining_time":11.15268182},
{"learn":[0.5062119708],"iteration":16,"passed_time":0.7999374407,"remaining_time":10.96384845},
{"learn":[0.5040575422],"iteration":17,"passed_time":0.8376021994,"remaining_time":10.79576168},
{"learn":[0.5031310428],"iteration":18,"passed_time":0.8756373118,"remaining_time":10.64590626},
{"learn":[0.5018051581],"iteration":19,"passed_time":0.9126333078,"remaining_time":10.49528304},
{"learn":[0.4994947938],"iteration":20,"passed_time":0.9519418582,"remaining_time":10.38069931},
{"learn":[0.4981219846],"iteration":21,"passed_time":0.9922073725,"remaining_time":10.28287641},
{"learn":[0.4969351758],"iteration":22,"passed_time":1.032757302,"remaining_time":10.19286554},
{"learn":[0.4952827914],"iteration":23,"passed_time":1.073454404,"remaining_time":10.1083623},
{"learn":[0.4938389814],"iteration":24,"passed_time":1.113597662,"remaining_time":10.02237895},
{"learn":[0.4924075348],"iteration":25,"passed_time":1.155734801,"remaining_time":9.957099825},
{"learn":[0.4912186884],"iteration":26,"passed_time":1.193019277,"remaining_time":9.853455507},
{"learn":[0.4893564525],"iteration":27,"passed_time":1.230256726,"remaining_time":9.754178325},
{"learn":[0.4881398375],"iteration":28,"passed_time":1.264351622,"remaining_time":9.635231325},
{"learn":[0.4865816791],"iteration":29,"passed_time":1.299043998,"remaining_time":9.52632265},
{"learn":[0.4848523103],"iteration":30,"passed_time":1.33379405,"remaining_time":9.422609579},
{"learn":[0.4835502436],"iteration":31,"passed_time":1.37003161,"remaining_time":9.333340342},
{"learn":[0.4817363664],"iteration":32,"passed_time":1.449164494,"remaining_time":9.529354399},
{"learn":[0.480039737],"iteration":33,"passed_time":1.486091987,"remaining_time":9.441054975},
{"learn":[0.4785962647],"iteration":34,"passed_time":1.520295711,"remaining_time":9.338959365},
{"learn":[0.4774787722],"iteration":35,"passed_time":1.554179654,"remaining_time":9.238734612},
{"learn":[0.476311599],"iteration":36,"passed_time":1.59039527,"remaining_time":9.155518714},
{"learn":[0.4747844712],"iteration":37,"passed_time":1.628331575,"remaining_time":9.084376156},
{"learn":[0.4732651705],"iteration":38,"passed_time":1.663322776,"remaining_time":8.99900271},
{"learn":[0.4718003056],"iteration":39,"passed_time":1.699585363,"remaining_time":8.922823156},
{"learn":[0.4712100217],"iteration":40,"passed_time":1.733405289,"remaining_time":8.836139156},
{"learn":[0.4697262501],"iteration":41,"passed_time":1.770692784,"remaining_time":8.769145216},
{"learn":[0.4684671247],"iteration":42,"passed_time":1.806974162,"remaining_time":8.69868957},
{"learn":[0.4672401392],"iteration":43,"passed_time":1.843231946,"remaining_time":8.629676836},
{"learn":[0.4664019305],"iteration":44,"passed_time":1.876245602,"remaining_time":8.547341076},
{"learn":[0.4652577387],"iteration":45,"passed_time":1.913145811,"remaining_time":8.484385771},
{"learn":[0.4643414213],"iteration":46,"passed_time":1.949461397,"remaining_time":8.42001412},
{"learn":[0.4635292321],"iteration":47,"passed_time":1.983057873,"remaining_time":8.34536855},
{"learn":[0.4620240007],"iteration":48,"passed_time":2.018591255,"remaining_time":8.280343719},
{"learn":[0.4607383986],"iteration":49,"passed_time":2.059500387,"remaining_time":8.238001549},
{"learn":[0.4596044869],"iteration":50,"passed_time":2.099060487,"remaining_time":8.190451703},
{"learn":[0.4585042718],"iteration":51,"passed_time":2.133248648,"remaining_time":8.122754467},
{"learn":[0.4573733434],"iteration":52,"passed_time":2.167138811,"remaining_time":8.055214072},
{"learn":[0.4560316267],"iteration":53,"passed_time":2.203108618,"remaining_time":7.996468319},
{"learn":[0.4553197178],"iteration":54,"passed_time":2.239539384,"remaining_time":7.940185087},
{"learn":[0.4543676925],"iteration":55,"passed_time":2.280976955,"remaining_time":7.901955879},
{"learn":[0.4533979393],"iteration":56,"passed_time":2.326222134,"remaining_time":7.876506525},
{"learn":[0.4524946322],"iteration":57,"passed_time":2.365562827,"remaining_time":7.83082867},
{"learn":[0.4516041445],"iteration":58,"passed_time":2.403478404,"remaining_time":7.780752123},
{"learn":[0.4505980468],"iteration":59,"passed_time":2.44362309,"remaining_time":7.738139785},
{"learn":[0.449541088],"iteration":60,"passed_time":2.483103586,"remaining_time":7.693550454},
{"learn":[0.4486963643],"iteration":61,"passed_time":2.527123777,"remaining_time":7.662891454},
{"learn":[0.4481264258],"iteration":62,"passed_time":2.564939932,"remaining_time":7.613393132},
{"learn":[0.4471330694],"iteration":63,"passed_time":2.603243029,"remaining_time":7.565675053},
{"learn":[0.4460704561],"iteration":64,"passed_time":2.63931965,"remaining_time":7.511909772},
{"learn":[0.4452504202],"iteration":65,"passed_time":2.676003161,"remaining_time":7.46037245},
{"learn":[0.4444348579],"iteration":66,"passed_time":2.716976013,"remaining_time":7.420994184},
{"learn":[0.4438003984],"iteration":67,"passed_time":2.758285541,"remaining_time":7.382470124},
{"learn":[0.4428776042],"iteration":68,"passed_time":2.794162334,"remaining_time":7.329614237},
{"learn":[0.4424432437],"iteration":69,"passed_time":2.830293635,"remaining_time":7.277897918},
{"learn":[0.4413900911],"iteration":70,"passed_time":2.867530367,"remaining_time":7.229407545},
{"learn":[0.4408160036],"iteration":71,"passed_time":2.904206061,"remaining_time":7.179842763},
{"learn":[0.4401823311],"iteration":72,"passed_time":2.943283266,"remaining_time":7.136453945},
{"learn":[0.4393526506],"iteration":73,"passed_time":2.985478517,"remaining_time":7.100597554},
{"learn":[0.4388804751],"iteration":74,"passed_time":3.0217627,"remaining_time":7.050779633},
{"learn":[0.4381172684],"iteration":75,"passed_time":3.057922269,"remaining_time":7.001032564},
{"learn":[0.4370709615],"iteration":76,"passed_time":3.097295914,"remaining_time":6.958859651},
{"learn":[0.4362944904],"iteration":77,"passed_time":3.133839468,"remaining_time":6.910517801},
{"learn":[0.4352849951],"iteration":78,"passed_time":3.175079644,"remaining_time":6.872640748},
{"learn":[0.4345627422],"iteration":79,"passed_time":3.214882587,"remaining_time":6.831625498},
{"learn":[0.4339930076],"iteration":80,"passed_time":3.249165017,"remaining_time":6.779122072},
{"learn":[0.432458437],"iteration":81,"passed_time":3.284532804,"remaining_time":6.729286721},
{"learn":[0.4320752403],"iteration":82,"passed_time":3.317101414,"remaining_time":6.674167905},
{"learn":[0.4312249854],"iteration":83,"passed_time":3.350749299,"remaining_time":6.621718853},
{"learn":[0.4304996209],"iteration":84,"passed_time":3.387851103,"remaining_time":6.576416848},
{"learn":[0.4296317389],"iteration":85,"passed_time":3.428210016,"remaining_time":6.537516774},
{"learn":[0.4290441386],"iteration":86,"passed_time":3.467098685,"remaining_time":6.495828571},
{"learn":[0.4285413137],"iteration":87,"passed_time":3.50686198,"remaining_time":6.455814099},
{"learn":[0.4276298949],"iteration":88,"passed_time":3.548603681,"remaining_time":6.419384188},
{"learn":[0.4267377683],"iteration":89,"passed_time":3.593330636,"remaining_time":6.388143353},
{"learn":[0.4258899695],"iteration":90,"passed_time":3.639256225,"remaining_time":6.358700438},
{"learn":[0.4250254044],"iteration":91,"passed_time":3.689249242,"remaining_time":6.335884568},
{"learn":[0.4242182383],"iteration":92,"passed_time":3.738529914,"remaining_time":6.311281683},
{"learn":[0.4235655264],"iteration":93,"passed_time":3.785541005,"remaining_time":6.2823872},
{"learn":[0.4227229355],"iteration":94,"passed_time":3.831353667,"remaining_time":6.251155984},
{"learn":[0.4220171406],"iteration":95,"passed_time":3.877094347,"remaining_time":6.219505514},
{"learn":[0.4216054101],"iteration":96,"passed_time":3.916726351,"remaining_time":6.177929192},
{"learn":[0.4212148967],"iteration":97,"passed_time":3.954599564,"remaining_time":6.13366463},
{"learn":[0.420589137],"iteration":98,"passed_time":3.993056039,"remaining_time":6.090418808},
{"learn":[0.4193617807],"iteration":99,"passed_time":4.037795348,"remaining_time":6.056693022},
{"learn":[0.418539887],"iteration":100,"passed_time":4.086832831,"remaining_time":6.029090018},
{"learn":[0.4178489201],"iteration":101,"passed_time":4.128303129,"remaining_time":5.990086894},
{"learn":[0.4170952971],"iteration":102,"passed_time":4.167504569,"remaining_time":5.947797784},
{"learn":[0.4164122989],"iteration":103,"passed_time":4.207789885,"remaining_time":5.907089646},
{"learn":[0.4158060429],"iteration":104,"passed_time":4.249948737,"remaining_time":5.868976827},
{"learn":[0.4152305622],"iteration":105,"passed_time":4.297061932,"remaining_time":5.837518096},
{"learn":[0.4143943294],"iteration":106,"passed_time":4.338245474,"remaining_time":5.797842082},
{"learn":[0.4138077755],"iteration":107,"passed_time":4.378262119,"remaining_time":5.756603897},
{"learn":[0.4131827241],"iteration":108,"passed_time":4.417659361,"remaining_time":5.71458688},
{"learn":[0.4124773154],"iteration":109,"passed_time":4.471842751,"remaining_time":5.691436229},
{"learn":[0.4118513491],"iteration":110,"passed_time":4.523980477,"remaining_time":5.665164741},
{"learn":[0.4112445089],"iteration":111,"passed_time":4.565851289,"remaining_time":5.625781053},
{"learn":[0.4106323531],"iteration":112,"passed_time":4.601839684,"remaining_time":5.579221564},
{"learn":[0.4099173604],"iteration":113,"passed_time":4.636074127,"remaining_time":5.530755099},
{"learn":[0.4091236447],"iteration":114,"passed_time":4.672110222,"remaining_time":5.48465113},
{"learn":[0.4087115125],"iteration":115,"passed_time":4.718577812,"remaining_time":5.450770921},
{"learn":[0.4081589036],"iteration":116,"passed_time":4.76204355,"remaining_time":5.413263181},
{"learn":[0.4073800973],"iteration":117,"passed_time":4.799332466,"remaining_time":5.368744792},
{"learn":[0.4066077954],"iteration":118,"passed_time":4.835425487,"remaining_time":5.323031419},
{"learn":[0.4059463547],"iteration":119,"passed_time":4.871182261,"remaining_time":5.277114116},
{"learn":[0.405313346],"iteration":120,"passed_time":4.909406657,"remaining_time":5.233995527},
{"learn":[0.4048351727],"iteration":121,"passed_time":4.953305356,"remaining_time":5.196910537},
{"learn":[0.4042307149],"iteration":122,"passed_time":4.993373372,"remaining_time":5.155759498},
{"learn":[0.4037268907],"iteration":123,"passed_time":5.027888845,"remaining_time":5.108983827},
{"learn":[0.4030487535],"iteration":124,"passed_time":5.064355915,"remaining_time":5.064355915},
{"learn":[0.4024216205],"iteration":125,"passed_time":5.102396086,"remaining_time":5.021405672},
{"learn":[0.4017085408],"iteration":126,"passed_time":5.137528831,"remaining_time":4.975716899},
{"learn":[0.4013383433],"iteration":127,"passed_time":5.191323176,"remaining_time":4.947979902},
{"learn":[0.4007714193],"iteration":128,"passed_time":5.239220189,"remaining_time":4.914307309},
{"learn":[0.4002582317],"iteration":129,"passed_time":5.27354639,"remaining_time":4.867888975},
{"learn":[0.399829858],"iteration":130,"passed_time":5.306324057,"remaining_time":4.820248571},
{"learn":[0.3991442884],"iteration":131,"passed_time":5.340370012,"remaining_time":4.773967132},
{"learn":[0.3987233189],"iteration":132,"passed_time":5.372969028,"remaining_time":4.726596814},
{"learn":[0.3982114855],"iteration":133,"passed_time":5.409948255,"remaining_time":4.683238788},
{"learn":[0.3974736557],"iteration":134,"passed_time":5.451017464,"remaining_time":4.643459321},
{"learn":[0.3964250352],"iteration":135,"passed_time":5.486498047,"remaining_time":4.598976304},
{"learn":[0.3959338368],"iteration":136,"passed_time":5.520506543,"remaining_time":4.553410506},
{"learn":[0.3952199969],"iteration":137,"passed_time":5.557332695,"remaining_time":4.510298999},
{"learn":[0.3943803467],"iteration":138,"passed_time":5.592782601,"remaining_time":4.466178911},
{"learn":[0.3939934591],"iteration":139,"passed_time":5.629668951,"remaining_time":4.423311319},
{"learn":[0.3936209669],"iteration":140,"passed_time":5.670006323,"remaining_time":4.383196378},
{"learn":[0.3930550512],"iteration":141,"passed_time":5.7046334,"remaining_time":4.338735262},
{"learn":[0.3922676992],"iteration":142,"passed_time":5.73990008,"remaining_time":4.29489027},
{"learn":[0.3917872856],"iteration":143,"passed_time":5.774741603,"remaining_time":4.250851458},
{"learn":[0.3914630691],"iteration":144,"passed_time":5.806942615,"remaining_time":4.205027411},
{"learn":[0.3909503651],"iteration":145,"passed_time":5.841810401,"remaining_time":4.161289601},
{"learn":[0.3904340801],"iteration":146,"passed_time":5.881991862,"remaining_time":4.121395658},
{"learn":[0.3899428369],"iteration":147,"passed_time":5.919269775,"remaining_time":4.079496737},
{"learn":[0.3896162821],"iteration":148,"passed_time":5.952110505,"remaining_time":4.034652087},
{"learn":[0.3891287276],"iteration":149,"passed_time":5.986115085,"remaining_time":3.99074339},
{"learn":[0.3884976179],"iteration":150,"passed_time":6.020707009,"remaining_time":3.947350953},
{"learn":[0.3878236609],"iteration":151,"passed_time":6.058793116,"remaining_time":3.90632714},
{"learn":[0.3872468307],"iteration":152,"passed_time":6.100185244,"remaining_time":3.867437704},
{"learn":[0.3865814045],"iteration":153,"passed_time":6.134229311,"remaining_time":3.823935155},
{"learn":[0.3863602671],"iteration":154,"passed_time":6.166731861,"remaining_time":3.77960985},
{"learn":[0.3858639689],"iteration":155,"passed_time":6.203499665,"remaining_time":3.738006208},
{"learn":[0.3852815291],"iteration":156,"passed_time":6.24135024,"remaining_time":3.697105556},
{"learn":[0.3848328424],"iteration":157,"passed_time":6.283149293,"remaining_time":3.658542626},
{"learn":[0.3842671622],"iteration":158,"passed_time":6.326496126,"remaining_time":3.620824827},
{"learn":[0.3837915595],"iteration":159,"passed_time":6.362928376,"remaining_time":3.579147211},
{"learn":[0.3832242738],"iteration":160,"passed_time":6.399341075,"remaining_time":3.537523949},
{"learn":[0.3828236502],"iteration":161,"passed_time":6.433979973,"remaining_time":3.495001467},
{"learn":[0.3825418413],"iteration":162,"passed_time":6.468369701,"remaining_time":3.452442724},
{"learn":[0.3822452706],"iteration":163,"passed_time":6.508225667,"remaining_time":3.412850045},
{"learn":[0.3819985999],"iteration":164,"passed_time":6.549185365,"remaining_time":3.373822764},
{"learn":[0.3814623562],"iteration":165,"passed_time":6.586572511,"remaining_time":3.332964403},
{"learn":[0.3807807347],"iteration":166,"passed_time":6.624725268,"remaining_time":3.292528127},
{"learn":[0.3804064095],"iteration":167,"passed_time":6.660620468,"remaining_time":3.251017133},
{"learn":[0.3798324227],"iteration":168,"passed_time":6.698788464,"remaining_time":3.210661926},
{"learn":[0.3792902489],"iteration":169,"passed_time":6.739412475,"remaining_time":3.171488224},
{"learn":[0.3789720933],"iteration":170,"passed_time":6.779245634,"remaining_time":3.131932194},
{"learn":[0.3787519776],"iteration":171,"passed_time":6.816799656,"remaining_time":3.091339379},
{"learn":[0.3781480559],"iteration":172,"passed_time":6.852251649,"remaining_time":3.04984611},
{"learn":[0.3776919063],"iteration":173,"passed_time":6.891287103,"remaining_time":3.00998747},
{"learn":[0.3772251624],"iteration":174,"passed_time":6.927786476,"remaining_time":2.969051347},
{"learn":[0.3769120361],"iteration":175,"passed_time":6.967610203,"remaining_time":2.929563381},
{"learn":[0.3763987858],"iteration":176,"passed_time":7.009521596,"remaining_time":2.890932636},
{"learn":[0.3758132798],"iteration":177,"passed_time":7.04768896,"remaining_time":2.850750591},
{"learn":[0.3754891041],"iteration":178,"passed_time":7.082743671,"remaining_time":2.809356428},
{"learn":[0.3749071637],"iteration":179,"passed_time":7.120036511,"remaining_time":2.768903088},
{"learn":[0.3745109261],"iteration":180,"passed_time":7.15637142,"remaining_time":2.728119492},
{"learn":[0.3742084363],"iteration":181,"passed_time":7.197572561,"remaining_time":2.689202935},
{"learn":[0.3739471214],"iteration":182,"passed_time":7.237361447,"remaining_time":2.649744355},
{"learn":[0.3735055825],"iteration":183,"passed_time":7.273860047,"remaining_time":2.609101973},
{"learn":[0.3730852158],"iteration":184,"passed_time":7.310260386,"remaining_time":2.568469865},
{"learn":[0.3724561503],"iteration":185,"passed_time":7.346875514,"remaining_time":2.527957166},
{"learn":[0.3717867609],"iteration":186,"passed_time":7.384513514,"remaining_time":2.487830756},
{"learn":[0.3713959424],"iteration":187,"passed_time":7.424193541,"remaining_time":2.448404253},
{"learn":[0.3710797454],"iteration":188,"passed_time":7.465953632,"remaining_time":2.40964641},
{"learn":[0.3703944738],"iteration":189,"passed_time":7.503571,"remaining_time":2.369548737},
{"learn":[0.3699899827],"iteration":190,"passed_time":7.54099151,"remaining_time":2.329416226},
{"learn":[0.3696751438],"iteration":191,"passed_time":7.578574879,"remaining_time":2.289361161},
{"learn":[0.3692622146],"iteration":192,"passed_time":7.615194498,"remaining_time":2.24904708},
{"learn":[0.3689886276],"iteration":193,"passed_time":7.656442106,"remaining_time":2.210107},
{"learn":[0.3686095073],"iteration":194,"passed_time":7.69755634,"remaining_time":2.171105634},
{"learn":[0.3681326607],"iteration":195,"passed_time":7.741648197,"remaining_time":2.132903075},
{"learn":[0.3675706705],"iteration":196,"passed_time":7.780841747,"remaining_time":2.093322907},
{"learn":[0.3672057848],"iteration":197,"passed_time":7.817228463,"remaining_time":2.053009495},
{"learn":[0.3666985751],"iteration":198,"passed_time":7.855082468,"remaining_time":2.013111587},
{"learn":[0.3662179478],"iteration":199,"passed_time":7.898719922,"remaining_time":1.974679981},
{"learn":[0.3655575248],"iteration":200,"passed_time":7.939476835,"remaining_time":1.935494353},
{"learn":[0.3650912143],"iteration":201,"passed_time":7.976913502,"remaining_time":1.895504198},
{"learn":[0.3646271861],"iteration":202,"passed_time":8.014514551,"remaining_time":1.855577261},
{"learn":[0.364227523],"iteration":203,"passed_time":8.053673547,"remaining_time":1.816024427},
{"learn":[0.3639771789],"iteration":204,"passed_time":8.099791914,"remaining_time":1.778003103},
{"learn":[0.3636704459],"iteration":205,"passed_time":8.167678785,"remaining_time":1.74455275},
{"learn":[0.3634152427],"iteration":206,"passed_time":8.213470842,"remaining_time":1.706179933},
{"learn":[0.3630880007],"iteration":207,"passed_time":8.258595319,"remaining_time":1.667600978},
{"learn":[0.3627006716],"iteration":208,"passed_time":8.302891359,"remaining_time":1.628796869},
{"learn":[0.3622963912],"iteration":209,"passed_time":8.351707173,"remaining_time":1.590801366},
{"learn":[0.3618391196],"iteration":210,"passed_time":8.395653428,"remaining_time":1.55180324},
{"learn":[0.3614367385],"iteration":211,"passed_time":8.438772889,"remaining_time":1.512610235},
{"learn":[0.3609762094],"iteration":212,"passed_time":8.485302113,"remaining_time":1.473972668},
{"learn":[0.360378451],"iteration":213,"passed_time":8.535216779,"remaining_time":1.43583086},
{"learn":[0.3598637428],"iteration":214,"passed_time":8.58601074,"remaining_time":1.397722679},
{"learn":[0.3595135352],"iteration":215,"passed_time":8.633778078,"remaining_time":1.359020623},
{"learn":[0.359320494],"iteration":216,"passed_time":8.679331861,"remaining_time":1.319898394},
{"learn":[0.3589432672],"iteration":217,"passed_time":8.724424476,"remaining_time":1.280649464},
{"learn":[0.358656997],"iteration":218,"passed_time":8.769756678,"remaining_time":1.241381082},
{"learn":[0.3582650091],"iteration":219,"passed_time":8.813019558,"remaining_time":1.201775394},
{"learn":[0.3579098173],"iteration":220,"passed_time":8.852442614,"remaining_time":1.161632741},
{"learn":[0.3574490427],"iteration":221,"passed_time":8.893182346,"remaining_time":1.121662638},
{"learn":[0.3569892004],"iteration":222,"passed_time":8.93287038,"remaining_time":1.081558297},
{"learn":[0.356619174],"iteration":223,"passed_time":8.975346874,"remaining_time":1.041781334},
{"learn":[0.356370485],"iteration":224,"passed_time":9.021336412,"remaining_time":1.002370712},
{"learn":[0.3559626168],"iteration":225,"passed_time":9.065088751,"remaining_time":0.9626642921},
{"learn":[0.3556148908],"iteration":226,"passed_time":9.105812204,"remaining_time":0.9226153334},
{"learn":[0.3552533042],"iteration":227,"passed_time":9.144506105,"remaining_time":0.8823646241},
{"learn":[0.3547619634],"iteration":228,"passed_time":9.184544767,"remaining_time":0.8422508301},
{"learn":[0.3545871773],"iteration":229,"passed_time":9.22730124,"remaining_time":0.8023740208},
{"learn":[0.3543002341],"iteration":230,"passed_time":9.266359235,"remaining_time":0.7621680756},
{"learn":[0.3539434095],"iteration":231,"passed_time":9.310061514,"remaining_time":0.7223323588},
{"learn":[0.3537150107],"iteration":232,"passed_time":9.355013774,"remaining_time":0.6825546531},
{"learn":[0.3534309869],"iteration":233,"passed_time":9.39874681,"remaining_time":0.6426493546},
{"learn":[0.3531945718],"iteration":234,"passed_time":9.44196518,"remaining_time":0.6026786285},
{"learn":[0.3530056207],"iteration":235,"passed_time":9.479750475,"remaining_time":0.562358079},
{"learn":[0.352720882],"iteration":236,"passed_time":9.51667639,"remaining_time":0.5220117851},
{"learn":[0.352245548],"iteration":237,"passed_time":9.557498968,"remaining_time":0.4818907043},
{"learn":[0.3517206149],"iteration":238,"passed_time":9.596350188,"remaining_time":0.4416730212},
{"learn":[0.3513838307],"iteration":239,"passed_time":9.640490602,"remaining_time":0.4016871084},
{"learn":[0.3510114032],"iteration":240,"passed_time":9.685360258,"remaining_time":0.3616939515},
{"learn":[0.3506599869],"iteration":241,"passed_time":9.724179889,"remaining_time":0.3214604922},
{"learn":[0.350435722],"iteration":242,"passed_time":9.760669886,"remaining_time":0.2811715605},
{"learn":[0.350187616],"iteration":243,"passed_time":9.799098358,"remaining_time":0.240961435},
{"learn":[0.3499100217],"iteration":244,"passed_time":9.835348767,"remaining_time":0.2007214034},
{"learn":[0.3496778148],"iteration":245,"passed_time":9.898809331,"remaining_time":0.1609562493},
{"learn":[0.3493025357],"iteration":246,"passed_time":9.94423672,"remaining_time":0.1207802031},
{"learn":[0.3489640394],"iteration":247,"passed_time":9.989445078,"remaining_time":0.08056004095},
{"learn":[0.3485446782],"iteration":248,"passed_time":10.03605254,"remaining_time":0.04030543188},
{"learn":[0.3479272702],"iteration":249,"passed_time":10.08570688,"remaining_time":0}
]}